README.md
setup.py
ProbabilisticPheRS/DirichletPriorOptimizer.py
ProbabilisticPheRS/MarginalFrequencyPrior.py
ProbabilisticPheRS/PDSBase.py
ProbabilisticPheRS/PDSSim.py
ProbabilisticPheRS/ProbabilisticPheRS.py
ProbabilisticPheRS/__init__.py
ProbabilisticPheRS.egg-info/PKG-INFO
ProbabilisticPheRS.egg-info/SOURCES.txt
ProbabilisticPheRS.egg-info/dependency_links.txt
ProbabilisticPheRS.egg-info/requires.txt
ProbabilisticPheRS.egg-info/top_level.txt